LICENSE
README.md
setup.py
kctools/__init__.py
kctools/kctools.py
kctools.egg-info/PKG-INFO
kctools.egg-info/SOURCES.txt
kctools.egg-info/dependency_links.txt
kctools.egg-info/top_level.txt
kctools/classes/__init__.py
kctools/classes/cache.py
kctools/classes/cuke.py
kctools/classes/dict.py
kctools/classes/lock.py
kctools/classes/map.py
kctools/classes/reg.py
kctools/classes/roll.py
kctools/classes/sub.py
kctools/classes/vec.py
kctools/classes/data/__init__.py
kctools/classes/data/config.py