Metadata-Version: 2.1
Name: kctools
Version: 24.11.0
Summary: miscellaneous elves
Home-page: https://github.com/kcstokely/kctools
Author: kevin c. stokely
Author-email: kcstokely@gmail.com
License: MIT
Platform: UNKNOWN
Classifier: Operating System :: OS Independent
Classifier: Programming Language :: Python :: 3
Classifier: License :: OSI Approved :: MIT License
